[
  {
    "question": "Какой модификатор доступа по умолчанию в Java?",
    "answers": [
      {"isCorrect": false, "text": "private"},
      {"isCorrect": true, "text": "default"},
      {"isCorrect": false, "text": "protected"}
    ]
  },
  {
    "question": "Какой из указанных типов данных не отностися к примитивным?",
    "answers": [
      {"isCorrect": true, "text": "String"},
      {"isCorrect": false, "text": "int"},
      {"isCorrect": false, "text": "boolean"}
    ]
  },
  {
    "question": " Какое ключевое словл используется в Java для создания объекта?",
    "answers": [
      {"isCorrect": true, "text": "new"},
      {"isCorrect": false, "text": "create"},
      {"isCorrect": false, "text": "instance"}
    ]
  },

  {
    "question": " Какой размер занимает тип данных int?",
    "answers": [
      {"isCorrect": false, "text": "8 bits"},
      {"isCorrect": true, "text": "32 bits"},
      {"isCorrect": false, "text": "64 bits"}
    ]
  }
]